{
  "last_update": "2025-10-17T02:48:21.861074+00:00",
  "channels": [
    {
      "tvg-id": "tensp",
      "tvg-logo": "https://raw.githubusercontent.com/hasanhabibmottakin/h2so4/main/img/t_sports.png",
      "name": "T Sports HD",
      "url": "https://d15.epicquesthero.com:999/hls/tenspk.m3u8?md5=eyVNqLQUarSa7BkcLt46-A&expires=1760676463"
    },
    {
      "tvg-id": "ptvpk",
      "tvg-logo": "https://crichdi.com/assets/uploads/channels/18.png",
      "name": "PTV Sports",
      "url": "https://d15.epicquesthero.com:999/hls/ptvpk.m3u8?md5=tdOadjvspy0KN0PDJuRp6g&expires=1760676462"
    },
    {
      "tvg-id": "star",
      "tvg-logo": "https://crichdi.com/assets/uploads/channels/19.png",
      "name": "Star sports 1 HD",
      "url": "https://d15.epicquesthero.com:999/hls/star1in.m3u8?md5=i3lkMIuDOhGBA6RHjcZO6Q&expires=1760676462"
    },
    {
      "tvg-id": "star1hi",
      "tvg-logo": "https://crichdi.com/assets/uploads/channels/19.png",
      "name": "Star sports 1 Hindi HD",
      "url": "https://d15.epicquesthero.com:999/hls/starhindi.m3u8?md5=uxTIBK4qQ0GcT68j8IQtuQ&expires=1760676463"
    },
    {
      "tvg-id": "sonyten1",
      "tvg-logo": "https://brand-websites-prod.s3.ap-south-1.amazonaws.com/sonypicturesnetworksindia/logo/21_266.png",
      "name": "Sony Ten 1",
      "url": "https://d15.epicquesthero.com:999/hls/ten1hd.m3u8?md5=JxRh6g3dyKP4k_y-zrYmUw&expires=1760676463"
    },
    {
      "tvg-id": "sonymax",
      "tvg-logo": "https://brand-websites-prod.s3.ap-south-1.amazonaws.com/sonypicturesnetworksindia/logo/25_276.png",
      "name": "Sony Ten 3",
      "url": "https://d15.epicquesthero.com:999/hls/sonyespnind.m3u8?md5=EfGs9RkSWT1rrw4cERqpBg&expires=1760676463"
    },
    {
      "tvg-id": "willowcricket",
      "tvg-logo": "https://crichdi.com/assets/uploads/channels/20.png",
      "name": "Willow Cricket",
      "url": "https://d15.epicquesthero.com:999/hls/willowusa.m3u8?md5=U_daX6gHZgaASpjZlvD_XQ&expires=1760676463"
    },
    {
      "tvg-id": "willowextra",
      "tvg-logo": "https://crichdi.com/assets/uploads/channels/55.png",
      "name": "Willow Extra",
      "url": "https://d15.epicquesthero.com:999/hls/willowextra.m3u8?md5=tGogqM1PD8TNGLYDSR9KlA&expires=1760676463"
    },
    {
      "tvg-id": "asportshd",
      "tvg-logo": "https://raw.githubusercontent.com/hasanhabibmottakin/h2so4/main/img/asports.jpg",
      "name": "A Sports HD",
      "url": "https://d15.epicquesthero.com:999/hls/asportshd.m3u8?md5=qF2dYuKZgul4diiZX7tPug&expires=1760676463"
    },
    {
      "tvg-id": "sscricket",
      "tvg-logo": "https://crichdi.com/assets/uploads/channels/50.gif",
      "name": "Super Cricket",
      "url": "https://d15.epicquesthero.com:999/hls/supercricket.m3u8?md5=0wPfpX46phTNQOWd-L1gkw&expires=1760676462"
    },
    {
      "tvg-id": "skys1",
      "tvg-logo": "https://crichdi.com/assets/uploads/channels/137.png",
      "name": "Sky Sports 1",
      "url": "https://d15.epicquesthero.com:999/hls/skysme.m3u8?md5=IDp5fnZxlm2cTkIARXpUWQ&expires=1760676462"
    },
    {
      "tvg-id": "skys2",
      "tvg-logo": "https://crichdi.com/assets/uploads/channels/138.png",
      "name": "Sky Sports 2",
      "url": "https://d15.epicquesthero.com:999/hls/skyscric.m3u8?md5=63_JLd6l3YEFcfHvNmAMJQ&expires=1760676463"
    },
    {
      "tvg-id": "skys3",
      "tvg-logo": "https://crichdi.com/assets/uploads/channels/144.png",
      "name": "Sky Sports 3",
      "url": "https://d15.epicquesthero.com:999/hls/skysact.m3u8?md5=xn6VfaQWEinAx__Y2yKhuA&expires=1760676462"
    },
    {
      "tvg-id": "skys4",
      "tvg-logo": "https://crichdi.com/assets/uploads/channels/139.png",
      "name": "Sky Sports 4",
      "url": "https://d15.epicquesthero.com:999/hls/skysgol.m3u8?md5=mmNtDutockKrGEMwcVohKQ&expires=1760676463"
    },
    {
      "tvg-id": "skys5",
      "tvg-logo": "https://crichdi.com/assets/uploads/channels/140.png",
      "name": "Sky Sports 5",
      "url": "https://d15.epicquesthero.com:999/hls/skysprem.m3u8?md5=BKF-XoKhtKWhVFdRy6fxAg&expires=1760676462"
    },
    {
      "tvg-id": "skystennis",
      "tvg-logo": "https://crichdi.com/assets/uploads/channels/12.gif",
      "name": "Skys Tennis",
      "url": "https://d15.epicquesthero.com:999/hls/skystennis.m3u8?md5=KPjq--CQyrDjHlzmtxQLgw&expires=1760676463"
    },
    {
      "tvg-id": "btsp1",
      "tvg-logo": "https://crichdi.com/assets/uploads/channels/10.gif",
      "name": "TNT Sports 1",
      "url": "https://d15.epicquesthero.com:999/hls/bbtsp1.m3u8?md5=7m72ZkP3lWj7eMQD7osZWg&expires=1760676463"
    },
    {
      "tvg-id": "btsp2",
      "tvg-logo": "https://crichdi.com/assets/uploads/channels/11.gif",
      "name": "TNT Sports 2",
      "url": "https://d15.epicquesthero.com:999/hls/bbtsp2.m3u8?md5=y9bWYkAvyfV60imRg4w2HQ&expires=1760676463"
    },
    {
      "tvg-id": "btsp3",
      "tvg-logo": "https://crichdi.com/assets/uploads/channels/12.gif",
      "name": "TNT Sports 3",
      "url": "https://d15.epicquesthero.com:999/hls/bbtsp3.m3u8?md5=pjtlpb6rou6aCOa135SSGg&expires=1760676463"
    },
    {
      "tvg-id": "btsp4",
      "tvg-logo": "https://crichdi.com/assets/uploads/channels/13.gif",
      "name": "TNT Sports 4",
      "url": "https://d15.epicquesthero.com:999/hls/bbtespn.m3u8?md5=z498HUT6fLi5ZrI2WRzFQA&expires=1760676463"
    },
    {
      "tvg-id": "laligauk",
      "tvg-logo": "https://crichdi.com/assets/uploads/channels/54.png",
      "name": "Laliga Hd",
      "url": "https://d15.epicquesthero.com:999/hls/laligauk.m3u8?md5=A0W_BrTwoAzILX6AExxWgw&expires=1760676463"
    },
    {
      "tvg-id": "ch5",
      "tvg-logo": "ch5",
      "name": "Ch5",
      "url": "https://d15.epicquesthero.com:999/hls/hdchnl5.m3u8?md5=Ml2V6RGaML4BgzZb_QM4dA&expires=1760676463"
    },
    {
      "tvg-id": "ch2",
      "tvg-logo": "",
      "name": "Premiar Sports",
      "url": "https://d15.epicquesthero.com:999/hls/hdchnl2.m3u8?md5=auzE7qJ7O9pp854neWSWSA&expires=1760676463"
    },
    {
      "tvg-id": "skysfor1",
      "tvg-logo": "skysfor1",
      "name": "Sky Sport F1",
      "url": null
    }
  ]
}