{
  "last_update": "2025-10-07T06:29:40.556656+00:00",
  "channels": [
    {
      "tvg-id": "ptvpk",
      "tvg-logo": "https://crichdi.com/assets/uploads/channels/18.png",
      "name": "PTV Sports",
      "url": "https://d15.epicquesthero.com:999/hls/ptvpk.m3u8?md5=vlEHK54to7Ke5pOEju9XIA&expires=1759825742"
    },
    {
      "tvg-id": "star",
      "tvg-logo": "https://crichdi.com/assets/uploads/channels/19.png",
      "name": "Star sports 1 HD",
      "url": "https://d15.epicquesthero.com:999/hls/star1in.m3u8?md5=SgUpK9c8rlIi4s7Cpp7KyA&expires=1759825742"
    },
    {
      "tvg-id": "star1hi",
      "tvg-logo": "https://crichdi.com/assets/uploads/channels/19.png",
      "name": "Star sports 1 Hindi HD",
      "url": "https://d15.epicquesthero.com:999/hls/starhindi.m3u8?md5=WaYikpgPLe8ovddocFkMlA&expires=1759825742"
    },
    {
      "tvg-id": "sonyten1",
      "tvg-logo": "https://brand-websites-prod.s3.ap-south-1.amazonaws.com/sonypicturesnetworksindia/logo/21_266.png",
      "name": "Sony Ten 1",
      "url": "https://d15.epicquesthero.com:999/hls/ten1hd.m3u8?md5=uL6J0oPA6wSyGAg5qcFwAA&expires=1759825742"
    },
    {
      "tvg-id": "sonymax",
      "tvg-logo": "https://brand-websites-prod.s3.ap-south-1.amazonaws.com/sonypicturesnetworksindia/logo/25_276.png",
      "name": "Sony Ten 3",
      "url": "https://d15.epicquesthero.com:999/hls/sonyespnind.m3u8?md5=idpe7XADIoZnJSRgmGkvmw&expires=1759825742"
    },
    {
      "tvg-id": "willowcricket",
      "tvg-logo": "https://crichdi.com/assets/uploads/channels/20.png",
      "name": "Willow Cricket",
      "url": "https://d15.epicquesthero.com:999/hls/willowusa.m3u8?md5=z9VkQSvf9e-q271RMyroaQ&expires=1759825742"
    },
    {
      "tvg-id": "willowextra",
      "tvg-logo": "https://crichdi.com/assets/uploads/channels/55.png",
      "name": "Willow Extra",
      "url": "https://d15.epicquesthero.com:999/hls/willowextra.m3u8?md5=Ihx_0oc1IWwqKvQMVsfkOg&expires=1759825742"
    },
    {
      "tvg-id": "asportshd",
      "tvg-logo": "https://crichdi.com/assets/uploads/channels/56.png",
      "name": "A Sports HD",
      "url": "https://d15.epicquesthero.com:999/hls/asportshd.m3u8?md5=KwLMwD7qzXGp7IYtU-SgRg&expires=1759825742"
    },
    {
      "tvg-id": "sscricket",
      "tvg-logo": "https://crichdi.com/assets/uploads/channels/50.gif",
      "name": "Super Cricket",
      "url": "https://d15.epicquesthero.com:999/hls/supercricket.m3u8?md5=6_JcU5F_r-sc5_mL6Gfj_Q&expires=1759825742"
    },
    {
      "tvg-id": "skys1",
      "tvg-logo": "https://crichdi.com/assets/uploads/channels/137.png",
      "name": "Sky Sports 1",
      "url": "https://d15.epicquesthero.com:999/hls/skysme.m3u8?md5=nuC1F8omzPoRO9Ssh6N2kg&expires=1759825742"
    },
    {
      "tvg-id": "skys2",
      "tvg-logo": "https://crichdi.com/assets/uploads/channels/138.png",
      "name": "Sky Sports 2",
      "url": "https://d15.epicquesthero.com:999/hls/skyscric.m3u8?md5=MjRfcuPrgcZ0yz5it5efHQ&expires=1759825742"
    },
    {
      "tvg-id": "skys3",
      "tvg-logo": "https://crichdi.com/assets/uploads/channels/144.png",
      "name": "Sky Sports 3",
      "url": "https://d15.epicquesthero.com:999/hls/skysact.m3u8?md5=Tyo6Tk82NirDtumhKnrUmA&expires=1759825742"
    },
    {
      "tvg-id": "skys4",
      "tvg-logo": "https://crichdi.com/assets/uploads/channels/139.png",
      "name": "Sky Sports 4",
      "url": "https://d15.epicquesthero.com:999/hls/skysgol.m3u8?md5=QR4WrEQC8M45YWAPMUmtqg&expires=1759825742"
    },
    {
      "tvg-id": "skys5",
      "tvg-logo": "https://crichdi.com/assets/uploads/channels/140.png",
      "name": "Sky Sports 5",
      "url": "https://d15.epicquesthero.com:999/hls/skysprem.m3u8?md5=l-KQc_T8OUS3lYv1RTmKww&expires=1759825742"
    },
    {
      "tvg-id": "skystennis",
      "tvg-logo": "https://crichdi.com/assets/uploads/channels/12.gif",
      "name": "Skys Tennis",
      "url": "https://d15.epicquesthero.com:999/hls/skystennis.m3u8?md5=0jt3KoTfuN5yJMafO270Qg&expires=1759825742"
    },
    {
      "tvg-id": "btsp1",
      "tvg-logo": "https://crichdi.com/assets/uploads/channels/10.gif",
      "name": "TNT Sports 1",
      "url": "https://d15.epicquesthero.com:999/hls/bbtsp1.m3u8?md5=E0kWAWWUufg5BcjlWjmV0A&expires=1759825742"
    },
    {
      "tvg-id": "btsp2",
      "tvg-logo": "https://crichdi.com/assets/uploads/channels/11.gif",
      "name": "TNT Sports 2",
      "url": "https://d15.epicquesthero.com:999/hls/bbtsp2.m3u8?md5=TzM3uP-vXXlezy6oGX416g&expires=1759825742"
    },
    {
      "tvg-id": "btsp3",
      "tvg-logo": "https://crichdi.com/assets/uploads/channels/12.gif",
      "name": "TNT Sports 3",
      "url": "https://d15.epicquesthero.com:999/hls/bbtsp3.m3u8?md5=wrvbWxVox6mgzNcAQjKgyQ&expires=1759825742"
    },
    {
      "tvg-id": "btsp4",
      "tvg-logo": "https://crichdi.com/assets/uploads/channels/13.gif",
      "name": "TNT Sports 4",
      "url": "https://d15.epicquesthero.com:999/hls/bbtespn.m3u8?md5=qCV720c67qbX-vgJSYN1_A&expires=1759825742"
    },
    {
      "tvg-id": "laligauk",
      "tvg-logo": "https://crichdi.com/assets/uploads/channels/54.png",
      "name": "Laliga Hd",
      "url": "https://d15.epicquesthero.com:999/hls/laligauk.m3u8?md5=54672UP1PI5HaBUa3t8iZw&expires=1759825742"
    },
    {
      "tvg-id": "ch5",
      "tvg-logo": "ch5",
      "name": "Ch5",
      "url": "https://d15.epicquesthero.com:999/hls/hdchnl5.m3u8?md5=eMPd_9DZqedbiWVhpnIESQ&expires=1759825742"
    },
    {
      "tvg-id": "ch2",
      "tvg-logo": "",
      "name": "Premiar Sports",
      "url": "https://d15.epicquesthero.com:999/hls/hdchnl2.m3u8?md5=FylE-wxsFHqRD7Y4XVCGIw&expires=1759825742"
    }
  ]
}